[
    {
        "Category": "Bedroom Collections",
        "Collection": "Bedroom Collections",
        "Collection URL": "https://www.mavinfurniture.com/products/bedrooms/adrienne/",
        "Collection Name": "Adrienne",
        "Collection Description": "The sleek yet elegant curves of the Adrienne sleigh design are the perfect blend of traditional and modern. The high headboard and footboard create a visual sanctuary for rest and relaxation. Crafted from the finest woods, all pieces are available in your choice of finishes. An upholstered headboard and footboard are also available to add texture and color to the room.",
        "Products": {
            "https://www.mavinfurniture.com/wp-content/uploads/2022/08/adrienne-panel-3.jpg": {
                "caption": "ADRIENNE BEDROOM GROUP: Adrienne Chest 8 ADE10267, Adrienne Nightstand 1 ADE10241, Adrienne Dresser 2 ADE10248, with Mirror 4 ADE10304, Adrienne Queen Sleigh Bed with High Footboard ADE10113. This group was crafted using solid maple with our 304 Charcoal stain and Adrienne standard hardware, BP19008-SS"
            },
            "https://www.mavinfurniture.com/wp-content/uploads/2022/08/adrienne-panel-12.jpg": {
                "caption": "Adrienne Queen Sleigh Bed with High Footboard ADE10113"
            },
            "https://www.mavinfurniture.com/wp-content/uploads/2022/08/11209210113AdrienneSleighBedQueenHighFBSILO-ALT-EDITED-hi.jpg": {
                "caption": "Adrienne Queen Sleigh Bed with High Footboard ADE10113"
            },
            "https://www.mavinfurniture.com/wp-content/uploads/2022/08/adrienne-panel-5.jpg": {
                "caption": "Adrienne Nightstand 1 ADE10241"
            },
            "https://www.mavinfurniture.com/wp-content/uploads/2022/08/adrienne-panel-7.jpg": {
                "caption": "Adrienne Nightstand 1 ADE10241"
            },
            "https://www.mavinfurniture.com/wp-content/uploads/2022/08/adrienne-panel-10.jpg": {
                "caption": "Adrienne Dresser 2 ADE10248, with Mirror 4 ADE10304"
            },
            "https://www.mavinfurniture.com/wp-content/uploads/2022/08/adrienne-panel-11.jpg": {
                "caption": "Adrienne Dresser 2 ADE10248, with Mirror 4 ADE10304"
            },
            "https://www.mavinfurniture.com/wp-content/uploads/2022/08/adrienne-panel-8.jpg": {
                "caption": "Adrienne Chest 8 ADE10267"
            },
            "https://www.mavinfurniture.com/wp-content/uploads/2022/08/adrienne-panel-9.jpg": {
                "caption": "Adrienne Chest 8 ADE10267"
            },
            "https://www.mavinfurniture.com/wp-content/uploads/2022/08/adrienne-upholstery-4.jpg": {
                "caption": "Adrienne Chest 3 ADE10262, Adrienne Nightstand 1 ADE10241, Adrienne Dresser 4 ADE10250, with Mirror 2 ADE10302, Adrienne Queen Upholstered Bed with High Footboard ADE10413. This group was crafted using solid oak with our 320 Sand stain, 112 Natural Linen fabric and Adrienne standard hardware, BP19008-SS."
            },
            "https://www.mavinfurniture.com/wp-content/uploads/2022/08/adrienne-upholstery-9.jpg": {
                "caption": "Adrienne Queen Upholstered Bed with High Footboard ADE10413"
            },
            "https://www.mavinfurniture.com/wp-content/uploads/2022/08/adrienne-upholstery-10-1.jpg": {
                "caption": "Adrienne Queen Upholstered Bed with High Footboard ADE10413"
            },
            "https://www.mavinfurniture.com/wp-content/uploads/2022/08/adrienne-upholstery-5.jpg": {
                "caption": "Adrienne Chest 3 ADE10262"
            },
            "https://www.mavinfurniture.com/wp-content/uploads/2022/08/adrienne-upholstery-6.jpg": {
                "caption": "Adrienne Chest 3 ADE10262"
            }
        }
    },
    {
        "Category": "Bedroom Collections",
        "Collection": "Bedroom Collections",
        "Collection URL": "https://www.mavinfurniture.com/products/bedrooms/longmeadow/",
        "Collection Name": "Adrienne",
        "Collection Description": "In every nuance of this luxurious collection, Longmeadow boasts a strong, refined tranquility. Classic details like large, inset headboard and footboard panels and chamfered edging add a timeless elegance to any room. Available in a variety of wood species and finishes, each piece is crafted by skilled artisans to ensure every detail is perfectly created to exact specifications.",
        "Products": {
            "https://www.mavinfurniture.com/wp-content/uploads/longmeadow-1.webp": {
                "caption": "Longmeadow Dresser 5 LMW11251, with Mirror 2 LMW11302, Longmeadow Queen Panel Bed with End Drawers LMW11473, Longmeadow Nightstand 4 LMW11244, Longmeadow Chest 8 LMW11267. This group was crafted using solid rustic cherry with our 113 Michaels stain and Longmeadow standard hardware, BP30214-909 (pull) and BP37160-909 (knob)."
            },
            "https://www.mavinfurniture.com/wp-content/uploads/2022/08/6994711433LongmeadowPanelBedQueenFootboarddrawersSILO-hi.jpg": {
                "caption": "Longmeadow Queen Panel Bed End Drawers LMW11473"
            },
            "https://www.mavinfurniture.com/wp-content/uploads/2022/08/10465711201LongmeadowNightstand1SILO_hi-1.jpg": {
                "caption": "Longmeadow Nightstand 4 LMW11244"
            },
            "https://www.mavinfurniture.com/wp-content/uploads/2022/08/7455711250LongmeadowDresser4SILO_hi-6.jpg": {
                "caption": "Longmeadow Dresser 5 LMW11251"
            },
            "https://www.mavinfurniture.com/wp-content/uploads/2022/08/13421011250LongmeadowDresser4SILO-ALT_hi-5.jpg": {
                "caption": "Longmeadow Dresser 5 LMW11251"
            },
            "https://www.mavinfurniture.com/wp-content/uploads/2022/08/12766411262LongmeadowChest3SILO-hi-4.jpg": {
                "caption": "Longmeadow Chest 8 LMW11267"
            },
            "https://www.mavinfurniture.com/wp-content/uploads/2022/08/10495911262LongmeadowChest3SILO-ALT-hi-3.jpg": {
                "caption": "Longmeadow Chest 8 LMW11267"
            },
            "https://www.mavinfurniture.com/wp-content/uploads/2022/08/102406LONGMEADOW-BEDROOM_hi.jpg": {
                "caption": "LONGMEADOW BEDROOM COLLECTION: Longmeadow Dresser 5 LMW11251 Longmeadow Nightstand 4 LMW11244, Longmeadow Chest 8 LMW11267, Longmeadow Queen Panel Bed Both Side Drawers LMW11463. This group was crafted using solid rustic cherry with our 113 Michaels stain and Longmeadow standard hardware, BP30214- 909 (pull) and BP37160-909 (knob)."
            },
            "https://www.mavinfurniture.com/wp-content/uploads/2022/08/148678LONGMEADOW-BEDROOM-DETAIL_hi.jpg": {
                "caption": "Panel Bed with Side Drawers Detail"
            },
            "https://www.mavinfurniture.com/wp-content/uploads/2022/08/longmeadow-drawer-8.jpg": {
                "caption": "End Drawer Detail"
            }
        }
    },
    {
        "Category": "Home Office Collection",
        "Collection": "Home Office Collection",
        "Collection URL": "https://www.mavinfurniture.com/products/tables/bookcases/",
        "Collection Name": "Bookcases",
        "Collection Description": "Our Bookcases\u2019 adjustable shelves offer versatility, allowing you to customize the display to suit your evolving collectiona and aesthetic preferences.",
        "Products": {
            "https://www.mavinfurniture.com/wp-content/uploads/MV_HomeOffice_SaybrookExecutive_view03-1.jpg": {
                "caption": "Left To Right: Saybrook Executive DeskWalnut & 100 Natural Sta"
            },
            "https://www.mavinfurniture.com/wp-content/uploads/MV_HomeOffice_SaybrookExecutive_view02-1.jpg": {
                "caption": "Left To Right: Brentwood BookcaseWalnut & 100 Natural StainHM"
            },
            "https://www.mavinfurniture.com/wp-content/uploads/MV_HomeOffice_SaybrookExecutive_view01-2.jpg": {
                "caption": "Left To Right: Saybrook Executive DeskWalnut & 100 Natural Sta"
            },
            "https://www.mavinfurniture.com/wp-content/uploads/MV_HomeOffice_SaybrookExecutive_view02D-1.jpg": {
                "caption": "Brentwood Bookcase Maple & 29P Ash PaintHMO2090B"
            },
            "https://www.mavinfurniture.com/wp-content/uploads/MV_HomeOffice_SaybrookExecutive_view02B-2.jpg": {
                "caption": "Left To Right: Brentwood BookcaseMaple & 29 Ash PaintHMO2090B"
            },
            "https://www.mavinfurniture.com/wp-content/uploads/MV_HomeOffice_SaybrookExecutive_view02C-1.jpg": {
                "caption": "Left To Right: Brentwood BookcaseMaple & 29 Ash PaintHMO2090B"
            },
            "https://www.mavinfurniture.com/wp-content/uploads/MV_HomeOffice_Marco_view04-extended-2.jpg": {
                "caption": "Oxford Bookcase Maple, 407 Black Silk Stain & 410 Honey StainHM"
            },
            "https://www.mavinfurniture.com/wp-content/uploads/MV_HomeOffice_Marco_view01-2.jpg": {
                "caption": "Left to Right: Oxford BookcaseMaple, 407 Black Silk Stain & 4"
            },
            "https://www.mavinfurniture.com/wp-content/uploads/MV_HomeOffice_Atwood_view04-1.jpg": {
                "caption": "Odessa Small Bookcase Maple, 404 Brindle Stain & 100 Natural Sta"
            },
            "https://www.mavinfurniture.com/wp-content/uploads/MV_HomeOffice_Atwood_view03-1.jpg": {
                "caption": "Odessa Small Bookcase Maple, 404 Brindle Stain & 100 Natural Stain HMO3090BS"
            },
            "https://www.mavinfurniture.com/wp-content/uploads/MV_HomeOffice01_OdessaTwoTone_7200px.jpg": {
                "caption": "Odessa Bookcase 2 HM03090A in Rustic Cherry with 409 Cocoa Exterior, 100 Natural Interior and A818-BN Hardware."
            },
            "https://www.mavinfurniture.com/wp-content/uploads/MV_HomeOffice02_OdesaBookcase_7200px.jpg": {
                "caption": "Odessa Bookcase HMO3090A in Maple and 400 Belair and A818-BN hardware."
            },
            "https://www.mavinfurniture.com/wp-content/uploads/ODEC30BS-M_OdessaBookcaseTwoTone_Angle_Rework.jpg": {
                "caption": "Odessa Large Bookcase HMO3090AL Rustic Cherry, 409 Cocoa Stain & 100 Natural Stain"
            },
            "https://www.mavinfurniture.com/wp-content/uploads/ODEC30BS-M_OdessaBookcaseTwoTone_Front_Rework.jpg": {
                "caption": "Odessa Large Bookcase HMO3090AL Rustic Cherry, 409 Cocoa Stain & 100 Natural Stain"
            },
            "https://www.mavinfurniture.com/wp-content/uploads/Odessa-Small-Bookcase_Maple_404Brindle_100Natural_Angle.jpg": {
                "caption": "Odessa Small Bookcase HMO3090BS Maple, 404 Brindle Stain & 100 Natural Stain"
            },
            "https://www.mavinfurniture.com/wp-content/uploads/Odessa-Small-Bookcase_Maple_404Brindle_100Natural_Front.jpg": {
                "caption": "Odessa Small BookcaseH MO3090BS Maple, 404 Brindle Stain & 100 Natural Stain"
            },
            "https://www.mavinfurniture.com/wp-content/uploads/Oxford-Bookcase_Maple_407BlackSilk_410Honey_Angle.jpg": {
                "caption": "Oxford Bookcase HMO2590A1Maple, 407 Black Silk Stain & 410 Honey Stain"
            },
            "https://www.mavinfurniture.com/wp-content/uploads/Oxford-Bookcase_Maple_407BlackSilk_410Honey_Front_rev00.jpg": {
                "caption": "Oxford Bookcase HMO2590A1Maple, 407 Black Silk Stain & 410 Honey Stain"
            },
            "https://www.mavinfurniture.com/wp-content/uploads/Brentwood_Bookcase_Maple_100Natural_Angle.jpg": {
                "caption": "Brentwood Bookcase HMO2090BMaple & 100 Natural Stain"
            },
            "https://www.mavinfurniture.com/wp-content/uploads/Brentwood_Bookcase_Maple_100Natural_Front.jpg": {
                "caption": "Brentwood Bookcase HMO2090BMaple & 100 Natural Stain"
            },
            "https://www.mavinfurniture.com/wp-content/uploads/Brentwood_Bookcase_Maple_Angle.jpg": {
                "caption": "Brentwood Bookcase HMO2090BMaple & 29P Ash Paint"
            },
            "https://www.mavinfurniture.com/wp-content/uploads/Brentwood_Bookcase_Maple_Front.jpg": {
                "caption": "Brentwood Bookcase HMO2090BMaple & 29P Ash Paint"
            }
        }
    },
    {
        "Category": "Bedroom Collections",
        "Collection": "Bedroom Collections",
        "Collection URL": "https://www.mavinfurniture.com/products/bedrooms/bartletts-island/",
        "Collection Name": "Adrienne",
        "Collection Description": "A lush rolling island known for its relaxed style of luxurious-simplicity, beauty and elegance inspires this collection\u2019s look. The panel bed, based on early 1800s style, features generous, beautifully carved posts and a graceful fireplace mantel top. A unique, curved crown and large raised panels complete the design. The arched panel bed is based upon the arched entryway into the original Bartlett Mansion. The towering 72-inch headboard features a gracefully arched mantel, flanked by Roman posts and raised panels. Both bed designs and coordinating pieces are available in a variety of wood species and finishes.",
        "Products": {
            "https://www.mavinfurniture.com/wp-content/uploads/2022/08/Bartletts-Island-King-Arched-Panel-Bed-group.jpg": {
                "caption": "BARTLETT\u2019S ISLAND BEDROOM GROUP: Bartlett\u2019s Island Chifferobe 3 BAR13258, Bartlett\u2019s Island Nightstand 1 BAR13241, Bartlett\u2019s Island Dresser 6 BAR13252, with Mirror 5 BAR13305, Bartlett\u2019s Island King Arched Panel Bed with High Footboard BAR13412. This group was crafted using solid rustic cherry with our 7992 Asbury stain and Bartlett\u2019s Island standard hardware, PA1218-VP (knob) and P2014-VP (ring pull)."
            },
            "https://www.mavinfurniture.com/wp-content/uploads/2022/08/130845BartlettsIslandKingArchedPANEL-BED-HighfbSILO-hi.jpg": {
                "caption": "Bartlett\u2019s Island King Arched Panel Bed with High Footboard BAR13412"
            },
            "https://www.mavinfurniture.com/wp-content/uploads/2022/08/86568BartlettsIslandKingArchedPANELBEDHighFbSILO-ALT-hi.jpg": {
                "caption": "Bartlett\u2019s Island King Arched Panel Bed with High Footboard BAR13412"
            },
            "https://www.mavinfurniture.com/wp-content/uploads/2022/08/102900BartlettsIslandDRESSER6-MIRROR5-SILO-ALT-hi.jpg": {
                "caption": "Bartlett\u2019s Island Dresser 6 BAR13252, with Mirror 5 BAR13305"
            },
            "https://www.mavinfurniture.com/wp-content/uploads/2022/08/46479BartlettsIslandDRESSER6-MIRROR5-SILO-hi.jpg": {
                "caption": "Bartlett\u2019s Island Dresser 6 BAR13252, with Mirror 5 BAR13305"
            },
            "https://www.mavinfurniture.com/wp-content/uploads/2022/08/22476BartlettsIslandNIGHTSTAND4-SILO-hi.jpg": {
                "caption": "Bartlett\u2019s Island Nightstand 1 BAR13241"
            },
            "https://www.mavinfurniture.com/wp-content/uploads/2022/08/23881BartlettsIslandNIGHTSTAND4-SILO-ALT-hi.jpg": {
                "caption": "Bartlett\u2019s Island Nightstand 1 BAR13241"
            },
            "https://www.mavinfurniture.com/wp-content/uploads/2022/08/Bartletts-Island-Queen-Panel-Bed-group-edit.jpg": {
                "caption": "BARTLETT\u2019S ISLAND BEDROOM GROUP: Bartlett\u2019s Island Dresser 1  BAR13247, with Mirror 4 BAR13304, Bartlett\u2019s Island Nightstand 1 BAR13241, Bartlett\u2019s Island Queen Panel Bed with Low Footboard BAR13123. This group was crafted using solid wormy maple with our 320 Sand stain and Bartlett\u2019s Island standard hardware, PA1218-VP (knob) and P2014-VP (ring pull)."
            },
            "https://www.mavinfurniture.com/wp-content/uploads/2022/08/56966BartlettsIslandQueenPANEL-BEDlowfbHO-SILO-hi.jpg": {
                "caption": "Bartlett\u2019s Island Queen Panel Bed with Low Footboard BAR13123"
            },
            "https://www.mavinfurniture.com/wp-content/uploads/2022/08/26781BartlettsIslandQueenPANEL-BEDlowfbSILO-hi.jpg": {
                "caption": "Bartlett\u2019s Island Queen Panel Bed with Low Footboard BAR13123"
            },
            "https://www.mavinfurniture.com/wp-content/uploads/2022/08/29487BartlettsIslandDRESSER1-MIRR0R4-SILO-hi.jpg": {
                "caption": "Bartlett\u2019s Island Dresser 1 BAR13247,  with Mirror 4 BAR13304"
            },
            "https://www.mavinfurniture.com/wp-content/uploads/2022/08/104375BartlettsIslandDRESSER1-MIRR0R4-SILO-ALT-hi.jpg": {
                "caption": "Bartlett\u2019s Island Dresser 1 BAR13247,  with Mirror 4 BAR13304"
            }
        }
    },
    {
        "Category": "Bedroom Collections",
        "Collection": "Bedroom Collections",
        "Collection URL": "https://www.mavinfurniture.com/products/bedrooms/atwood/",
        "Collection Name": "Adrienne",
        "Collection Description": "Breathe new life with a contemporary spin on traditional design. With clean lines and quality workmanship as the hallmark of this collection, Atwood defines what it truly means to be classically modern. Available in three bed designs and many coordinating pieces in a variety of wood species and finishes. Each piece is crafted by skilled artisans to exact specifications.",
        "Products": {
            "https://www.mavinfurniture.com/wp-content/uploads/2022/08/24569ATWOOD_PANEL_BED_RS_hi-3.jpg": {
                "caption": "Atwood Queen Panel Bed with End Drawers ATD08473"
            },
            "https://www.mavinfurniture.com/wp-content/uploads/2022/08/86733ATWOOD_PANEL_BED_FRONT_hi.jpg": {
                "caption": "Atwood Queen Panel Bed with End Drawers ATD08473"
            },
            "https://www.mavinfurniture.com/wp-content/uploads/2022/08/1828ATWOOD_PANEL_BED_SIL0_SIDE_hi.jpg": {
                "caption": "Atwood Queen Panel Bed with End Drawers ATD08473"
            },
            "https://www.mavinfurniture.com/wp-content/uploads/2022/08/64228ATD08247-M-front_hi.jpg": {
                "caption": "Atwood Dresser 1 ATD08247, with Atwood Dresser 1 ATD08247, with Mirror 4 ATD8304 Detail"
            },
            "https://www.mavinfurniture.com/wp-content/uploads/2022/08/11198ATD08247-M_3-4_hi.jpg": {
                "caption": "Atwood Dresser 1 ATD08247, with Atwood Dresser 1 ATD08247, with Mirror 4 ATD8304 Detail"
            },
            "https://www.mavinfurniture.com/wp-content/uploads/2022/08/62310ATWOOD_GRIDWORK_BED_RS_hi.jpg": {
                "caption": "ATWOOD BEDROOM GROUP: Atwood Armoire 2 ATD08255, Atwood Nightstand 1 ATD08241, Atwood Dresser 3 ATD08249, with Mirror 5 ATD08305, Atwood Queen Gridwork Bed with High Footboard ATD08613. This group was crafted using solid maple with our 230 Onyx stain and Atwood standard hardware, BP19008-SS."
            },
            "https://www.mavinfurniture.com/wp-content/uploads/2022/08/11534Q_GRIDWORK_BED_SILO_HO_hi.jpg": {
                "caption": "Atwood Queen Gridwork Bed with High Footboard ATD08613"
            },
            "https://www.mavinfurniture.com/wp-content/uploads/2022/08/58067Lindsey_Dark_Bed_Silo_Alt_EDIT2_hi.jpg": {
                "caption": "Atwood Queen Gridwork Bed with High Footboard ATD08613"
            },
            "https://www.mavinfurniture.com/wp-content/uploads/2022/08/28620Q_GRIDWORK_BED_SILO_ALT_hi.jpg": {
                "caption": "Atwood Queen Gridwork Bed with High Footboard ATD08613"
            },
            "https://www.mavinfurniture.com/wp-content/uploads/2022/08/111787ATWOOD-PANELRetouch3_hi-2.jpg": {
                "caption": "ATWOOD BEDROOM GROUP: Atwood Dresser 7 ATD08280, with Mirror 4 ATD08304, Atwood Nightstand 1 ATD08241, Atwood Chest 3 ATD08262, Atwood Queen Spindle Bed with Low Footboard ATD08123. This group was crafted using solid rustic cherry with our 113 Michaels stain and Atwood standard hardware, BP19008-SS."
            },
            "https://www.mavinfurniture.com/wp-content/uploads/2022/08/138682Atwood_Slat_Bed_SiloRetouch2_hi.jpg": {
                "caption": "Atwood Queen Spindle Bed with Low Footboard ATD08123"
            },
            "https://www.mavinfurniture.com/wp-content/uploads/2022/08/71005Atwood_Slat_Bed_Silo_AltRetouch2_hi.jpg": {
                "caption": "Atwood Queen Spindle Bed with Low Footboard ATD08123"
            },
            "https://www.mavinfurniture.com/wp-content/uploads/2022/08/atwood.jpg": {
                "caption": "Atwood Queen Panel Bed with Low Footboard ATD08423"
            },
            "https://www.mavinfurniture.com/wp-content/uploads/2022/08/123354Atwood_Panel_Bed_Silo_AltRetouch_hi.jpg": {
                "caption": "Atwood Queen Panel Bed with Low Footboard ATD08423"
            },
            "https://www.mavinfurniture.com/wp-content/uploads/2022/08/45010ATWOOD_WARDROBE_SILOedit2_hi.jpg": {
                "caption": "Atwood Chifferobe 2 ATD08256"
            },
            "https://www.mavinfurniture.com/wp-content/uploads/2022/08/79602ATWOOD_WARDROBE_SILO_ALTedit2_hi.jpg": {
                "caption": "Atwood Chifferobe 2 ATD08256"
            }
        }
    },
    {
        "Category": "Bedroom Collections",
        "Collection": "Bedroom Collections",
        "Collection URL": "https://www.mavinfurniture.com/products/bedrooms/vineyard-haven/",
        "Collection Name": "Adrienne",
        "Collection Description": "Simple yet sophisticated, Vineyard Haven features luxurious detailing. The classically patterned clean style appeals to both masculine and feminine influences with chiseled edges and soft details. Available in wood or upholstered bed styles, this collection is available in a variety of wood species and finishes. An array of coordinating nightstands, dressers, mirrors and chests are also available.",
        "Products": {
            "https://www.mavinfurniture.com/wp-content/uploads/2022/08/147352VINEYARD_HAVEN_K_UPH_VIGN-hi.jpg": {
                "caption": "Vineyard Haven King Upholstered Bed with End Drawers VDH06472 Detail"
            },
            "https://www.mavinfurniture.com/wp-content/uploads/2022/08/82114VINEYARD_HAVEN_K_UPH_SILO_HO-hi.jpg": {
                "caption": "Vineyard Haven King Upholstered Bed with End Drawers VDH06472"
            },
            "https://www.mavinfurniture.com/wp-content/uploads/2022/08/120252VINEYARD_HAVEN_K_UPH_SILO_ALT-hi.jpg": {
                "caption": "Vineyard Haven King Upholstered Bed with End Drawers VDH06472"
            },
            "https://www.mavinfurniture.com/wp-content/uploads/2022/08/Vineyard-Haven_Chest-convert-retouch-1.jpg": {
                "caption": "VINEYARD HAVEN BEDROOM GROUP: Vineyard Haven Queen Panel Bed with End Drawers VDH06113, Vineyard Haven Nightstand 4 VDH06244, Vineyard Haven Chest 7 VDH06266, Vineyard Haven Dresser 2 VDH06248, with Mirror 2 VDH06302. This group was crafted using solid maple with our 228 Rich Tobacco stain and Vineyard Haven standard hardware, 920240-904 (ring pull) and 24409-904 (knob)."
            },
            "https://www.mavinfurniture.com/wp-content/uploads/2022/08/Vineyard-Haven-Alt-retouch-1-11.jpg": {
                "caption": "VINEYARD HAVEN BEDROOM GROUP: Vineyard Haven Queen Panel Bed with High Footboard VDH06413, Vineyard Haven Nightstand 4 VDH06244, Vineyard Haven Chest 7 VDH06266. This group was crafted using solid maple with our 228 Rich Tobacco stain and Vineyard Haven standard hardware, 920240-904 (ring pull) and 24409-904 (knob)."
            },
            "https://www.mavinfurniture.com/wp-content/uploads/2022/08/99190Vineyard_Haven_Storage_Bed_Silo-Hi-Edit.jpg": {
                "caption": "Vineyard Haven Queen Panel Bed with End Drawers VDH06173"
            },
            "https://www.mavinfurniture.com/wp-content/uploads/2022/08/23511Vineyard_Haven_Storage_Bed_Silo_Alt-Hi-1.jpg": {
                "caption": "Vineyard Haven Queen Panel Bed with End Drawers VDH06173"
            },
            "https://www.mavinfurniture.com/wp-content/uploads/2022/08/31440VINEYARD_HAVEN_NIGHTSTAND_SILO-hi-7.jpg": {
                "caption": "Vineyard Haven Nightstand 4 VDH06244"
            },
            "https://www.mavinfurniture.com/wp-content/uploads/2022/08/125039VINEYARD_HAVEN_NIGHTSTAND_SILO_ALT-hi-8.jpg": {
                "caption": "Vineyard Haven Nightstand 4 VDH06244"
            },
            "https://www.mavinfurniture.com/wp-content/uploads/2022/08/38855VINEYARD_HAVEN_DRESSER_MIRROR_SILO-hi-4.jpg": {
                "caption": "Vineyard Haven Dresser 2 VDH06248, with Mirror 2 VDH06302"
            },
            "https://www.mavinfurniture.com/wp-content/uploads/2022/08/109016VINEYARD_HAVEN_DRESSER_MIRROR_SILO_ALY-hi-3.jpg": {
                "caption": "Vineyard Haven Dresser 2 VDH06248, with Mirror 2 VDH06320"
            },
            "https://www.mavinfurniture.com/wp-content/uploads/2022/08/43806VINEYARD_HAVEN_CHEST_SILOretouch1-hi-6.jpg": {
                "caption": "Vineyard Haven Chest 7 VDH06266"
            },
            "https://www.mavinfurniture.com/wp-content/uploads/2022/08/18477VINEYARD_HAVEN_CHEST_SILO_ALTretouch1-hi-5.jpg": {
                "caption": "Vineyard Haven Chest 7 VDH06266"
            }
        }
    },
    {
        "Category": "Bedroom Collections",
        "Collection": "Bedroom Collections",
        "Collection URL": "https://www.mavinfurniture.com/products/bedrooms/kingsport/",
        "Collection Name": "Adrienne",
        "Collection Description": "The Kingsport collection offers refined lines and curve appeal for your style conscious and creative tastes. Our panel bed design radiates strength and elegance in any choice of stain. While the upholstered bed combines the beauty of solid wood with subtle curves and rich fabrics. Coordinating nightstands, dressers, mirrors and chests are also available to complement either bed design choice.",
        "Products": {
            "https://www.mavinfurniture.com/wp-content/uploads/KINGSPORT_K_SLEIGH_BEDROOM_RS.jpg": {
                "caption": "Kingsport King Sleigh Panel Bed with Low Footboard KGP03522. Nightstand 4 KGP03244, Chest 3 KGP03262, Dresser 2 KGP03248 and Mirror 4 KGP03304 in Rustic Cherry, 409 Cocoa stain with standard hardware."
            },
            "https://www.mavinfurniture.com/wp-content/uploads/KINGSPORT_K_SLEIGH_BEDROOM_WS_1.jpg": {
                "caption": "Kingsport King Sleigh Panel Bed with Low Footboard KGP03522."
            },
            "https://www.mavinfurniture.com/wp-content/uploads/KINGSPORT_K_SLEIGH_BEDROOM_DETAILS_5.jpg": {
                "caption": "Kingsport Dresser 2 KGP03248 and Mirror 4 KGP03304 in Rustic Cherry, 409 Cocoa stain with standard hardware."
            },
            "https://www.mavinfurniture.com/wp-content/uploads/KINGSPORT_K_SLEIGH_BEDROOM_DETAILS_4.jpg": {
                "caption": "Kingsport King Sleigh Panel Bed Low Footboard KGP03522"
            },
            "https://www.mavinfurniture.com/wp-content/uploads/KINGSPORT_K_SLEIGH_BEDROOM_DETAILS_3.jpg": {
                "caption": "Kingsport King Sleigh Panel Bed KGP03522"
            },
            "https://www.mavinfurniture.com/wp-content/uploads/KINGSPORT_K_SLEIGH_BEDROOM_DETAILS_2.jpg": {
                "caption": "Kingsport King Sleigh Panel Bed with Low Footboard KGP03522"
            },
            "https://www.mavinfurniture.com/wp-content/uploads/KINGSPORT_K_SLEIGH_BEDROOM_DETAILS_1.jpg": {
                "caption": "Kingsport King Sleigh Panel Bed Low Footboard KGP03522"
            },
            "https://www.mavinfurniture.com/wp-content/uploads/KINGSPORT_K_SLEIGH_BEDROOM_Chest_WS_.jpg": {
                "caption": "Kingsport King Sleigh Panel Bed with Low Footboard KGP03522 and Chest 3 KGP03262 in Rustic Cherry, 409 Cocoa stain with standard hardware."
            },
            "https://www.mavinfurniture.com/wp-content/uploads/KINGSPORT_K_SLEIGH_BED_SILO_HO.jpg": {
                "caption": "Kingsport King Sleigh Panel Bed with Low Footboard KGP0352 in Rustic Cherry, 409 Cocoa stain with standard hardware."
            },
            "https://www.mavinfurniture.com/wp-content/uploads/KINGSPORT_K_SLEIGH_BED_SILO_ALT.jpg": {
                "caption": "Kingsport King Sleigh Panel Bed with Low Footboard KGP0352 in Rustic Cherry, 409 Cocoa stain with standard hardware."
            }
        }
    },
    {
        "Category": "Bedroom Collections",
        "Collection": "Bedroom Collections",
        "Collection URL": "https://www.mavinfurniture.com/products/bedrooms/charleston/",
        "Collection Name": "Adrienne",
        "Collection Description": "Elegant southern living is showcased in this modern farmhouse collection. Ornate edges with intricate craftsmanship welcome a charm all of its own with inset slatted panels and strong lines. Available in a variety of wood species and finishes, each piece is crafted by skilled artisans to exact specifications. Coordinating nightstands, dressers, mirrors and chests are also available.",
        "Products": {
            "https://www.mavinfurniture.com/wp-content/uploads/2022/07/charleston-archedpanel.jpg": {
                "caption": "CHARLESTON BEDROOM GROUP: Charleston Dresser 6 CHA15252, with Mirror 5 CHA15305, Charleston Nightstand 5 CHA15245, Charleston Chifferobe 1 CHA 15256, Charleston King Arched Panel Bed with Low Footboard CHA15122. This group was crafted using solid maple with our 401 Cider stain (bed, nightstand & mirror) and 1P SAV White paint with Savannah glazing and Charleston standard hardware, 24409-904 (knob) and 920240-904 (ring pull)."
            },
            "https://www.mavinfurniture.com/wp-content/uploads/2022/08/16432CHA_KING_SILO_HO_hi.jpg": {
                "caption": "Charleston King Arched Panel Bed with Low Footboard CHA15122"
            },
            "https://www.mavinfurniture.com/wp-content/uploads/2022/08/7502CHA_KING_SILO_3_4_hi.jpg": {
                "caption": "Charleston King Arched Panel Bed with Low Footboard CHA15122"
            },
            "https://www.mavinfurniture.com/wp-content/uploads/2022/08/56127CHA_DR6_MIR5_SILO_HO_hi.jpg": {
                "caption": "Charleston Dresser 6 CHA15252, with Mirror 5 CHA15305"
            },
            "https://www.mavinfurniture.com/wp-content/uploads/2022/08/75770CHA_DR6_MIR5_SILO_3-4_hi.jpg": {
                "caption": "Charleston Dresser 6 CHA15252, with Mirror 5 CHA15305"
            },
            "https://www.mavinfurniture.com/wp-content/uploads/2022/08/132765CHA_CHIFFEROBE2_SILO_HO_hi.jpg": {
                "caption": "Charleston Chifferobe 1 CHA15256"
            },
            "https://www.mavinfurniture.com/wp-content/uploads/2022/08/14273CHA_CHIFFEROBE2_SILO_3-4_hi.jpg": {
                "caption": "Charleston Chifferobe 1 CHA15256"
            },
            "https://www.mavinfurniture.com/wp-content/uploads/2022/08/122996Charlelston_Queen_Bedroom_RS_hi.jpg": {
                "caption": "CHARLESTON BEDROOM GROUP: Charleston Dresser 7 CHA15280, with Mirror 4 CHA15304, Charleston Nightstand 1 CHA15241, Charleston Chest 7 CHA15266, Charleston Queen Louver Panel Bed with End Drawers CHA151473. This group was crafted using solid rustic cherry with our 401 Cider stain and Charleston standard hardware, 24409-904 (knob) and 920240-904 (ring pull)."
            },
            "https://www.mavinfurniture.com/wp-content/uploads/2022/08/116401CHA_NIGHTSTAND5_SILO_HO_hi.jpg": {
                "caption": "Charleston Nightstand 5 CHA15245"
            },
            "https://www.mavinfurniture.com/wp-content/uploads/2022/08/77318CHA_NIGHTSTAND5_SILO_3-4_hi.jpg": {
                "caption": "Charleston Nightstand 5 CHA15245"
            },
            "https://www.mavinfurniture.com/wp-content/uploads/2022/08/78621CHA_CHEST7_SILO_HO_hi.jpg": {
                "caption": "Charleston Chest 7 CHA15266"
            },
            "https://www.mavinfurniture.com/wp-content/uploads/2022/08/139970CHA_CHEST7_SILO_3-4_hi.jpg": {
                "caption": "Charleston Chest 7 CHA15266"
            },
            "https://www.mavinfurniture.com/wp-content/uploads/2022/08/53531CHA_DR7_MIR_SILO_HO_hi.jpg": {
                "caption": "Charleston Dresser 7 CHA15280, with Mirror 4 CHA15304"
            },
            "https://www.mavinfurniture.com/wp-content/uploads/2022/08/87875CHA_DR7_MIR_SILO_3-4_hi.jpg": {
                "caption": "Charleston Dresser 7 CHA15280, with Mirror 4 CHA15304"
            }
        }
    },
    {
        "Category": "Occasional Collection",
        "Collection": "Occasional Collection",
        "Collection URL": "https://www.mavinfurniture.com/products/tables/barley/",
        "Collection Name": "Barley Occasionals",
        "Collection Description": null,
        "Products": {
            "https://www.mavinfurniture.com/wp-content/uploads/BARLEY_GROUP_SHOT.jpg": {
                "caption": "Barley Sofa Table OCA0191C, Barley Square End Table OCA0192C, Ba"
            },
            "https://www.mavinfurniture.com/wp-content/uploads/42_BARLEY_RECT_COFFEE_TABLE_SILO_HO.jpg": {
                "caption": "Barley Rectangle Coffee Table OCA0194C in solid Maple with our 4"
            },
            "https://www.mavinfurniture.com/wp-content/uploads/42_BARLEY_RECT_COFFEE_TABLE_SILO_ALT.jpg": {
                "caption": "Barley Rectangle Coffee Table OCA0194C in solid Maple with our 4"
            },
            "https://www.mavinfurniture.com/wp-content/uploads/BARLEY_ROUND_COFFEE_TABLE_SILO_HO.jpg": {
                "caption": "Barley Round Coffee Table OCA0189B in solid Maple with our 400 B"
            },
            "https://www.mavinfurniture.com/wp-content/uploads/BARLEY_ROUND_COFFEE_TABLE_SILO_ALT.jpg": {
                "caption": "Barley Round Coffee Table OCA0189B in solid Maple with our 400 B"
            },
            "https://www.mavinfurniture.com/wp-content/uploads/24_SQUARE_COFFEE_TABLE_SILO_HO.jpg": {
                "caption": "Barley Square End Table OCA0192C in solid Maple with our 400 Bel"
            },
            "https://www.mavinfurniture.com/wp-content/uploads/24_SQUARE_COFFEE_TABLE_SILO_ALT.jpg": {
                "caption": "Barley Square End Table OCA0192C in solid Maple with our 400 Bel"
            },
            "https://www.mavinfurniture.com/wp-content/uploads/24_ROUND_END_TABLE_SILO_HO.jpg": {
                "caption": "Barley Round End Table OCA0188C in Maple with 403 Indigo Stain"
            },
            "https://www.mavinfurniture.com/wp-content/uploads/24_ROUND_END_TABLE_SILO_ALT.jpg": {
                "caption": "Barley Round End Table OCA0188C in Maple with 403 Indigo Stain"
            },
            "https://www.mavinfurniture.com/wp-content/uploads/60-X-18_SOFA_TABLE_SILO_HO.jpg": {
                "caption": "Barley Sofa Table OCA0191C in solid Maple with our 400 Belair St"
            },
            "https://www.mavinfurniture.com/wp-content/uploads/60-X-18_SOFA_TABLE_SILO_ALT.jpg": {
                "caption": "Barley Sofa Table OCA0191C in solid Maple with our 400 Belair St"
            }
        }
    },
    {
        "Category": "Occasional Collection",
        "Collection": "Occasional Collection",
        "Collection URL": "https://www.mavinfurniture.com/products/tables/saybrook/",
        "Collection Name": "Saybrook Occasionals",
        "Collection Description": null,
        "Products": {
            "https://www.mavinfurniture.com/wp-content/uploads/SAYBROOK_GROUP_SHOT.jpg": {
                "caption": "L-R: Saybrook Chairside Chest OCA1693A, End Table OCA1692C, Square Coffee Table OCA1695B, Sofa Table, OCA1691C, Rectangle Coffee Table OCA1694C, Console Table OCA1690B. Chairside Chest, Sofa Table and Rectangle Coffee Table in Oak with 401 Cider Stain.  End Table, Square Coffee Table and Console Table in Oak with 407 Black Silk Stain. All tables feature standard hardware, 625-160SBZ."
            },
            "https://www.mavinfurniture.com/wp-content/uploads/MV_HomeOffice03_SaybrookExecutiveDeskFront_7200px.jpg": {
                "caption": "Saybrook Executive Desk HMO1698A in Oak and 401 Cider stain. Saybrook Console Table 1 OCA1690B in Oak and 400 Belair stain."
            },
            "https://www.mavinfurniture.com/wp-content/uploads/MV_HomeOffice03_SaybrookConsoleTable_7200px.jpg": {
                "caption": "Saybrook Console Table 1 OCA1690B in Oak and 400 Belair stain."
            },
            "https://www.mavinfurniture.com/wp-content/uploads/20X24_SAYBROOK_CHAIRSIDE_CHEST_SILO_HO.jpg": {
                "caption": "Saybrook Chairside Chest OCA1693A in Oak with 401 Cider Stain wi"
            },
            "https://www.mavinfurniture.com/wp-content/uploads/20X24_SAYBROOK_CHAIRSIDE_CHEST_SILO_ALT.jpg": {
                "caption": "Saybrook Chairside Chest OCA1693A in Oak with 401 Cider Stain wi"
            },
            "https://www.mavinfurniture.com/wp-content/uploads/24__SAYBROOK_END_TABLE_SILO_HO.jpg": {
                "caption": "Saybrook End Table OCA1692C Oak with 407 Black Silk Stain with s"
            },
            "https://www.mavinfurniture.com/wp-content/uploads/24__SAYBROOK_END_TABLE_SILO_ALT.jpg": {
                "caption": "24__SAYBROOK_END_TABLE_SILO_ALT"
            },
            "https://www.mavinfurniture.com/wp-content/uploads/42_-_SAYBROOK_SQ_HO.jpg": {
                "caption": "Saybrook Square Coffee Table OCA1695B Oak with 407 Black Silk St"
            },
            "https://www.mavinfurniture.com/wp-content/uploads/42_-_SAYBROOK_SQ_ALT.jpg": {
                "caption": "Saybrook Square Coffee Table OCA1695B Oak with 407 Black Silk St"
            },
            "https://www.mavinfurniture.com/wp-content/uploads/54X-30-_SAYBROOK_-REC_-SILO_HO.jpg": {
                "caption": "Rectangle Coffee Table OCA1694C in Oak with 401 Cider Stain with"
            },
            "https://www.mavinfurniture.com/wp-content/uploads/54X-30_SAYBROOK_REC_SILO_ALT.jpg": {
                "caption": "Rectangle Coffee Table OCA1694C in Oak with 401 Cider Stain with"
            },
            "https://www.mavinfurniture.com/wp-content/uploads/60X18_SAYBROOK_SOFA_TABLE_SILO_HO.jpg": {
                "caption": "Saybrook Sofa Table OCA1691C in Oak with 401 Cider Stain with st"
            },
            "https://www.mavinfurniture.com/wp-content/uploads/60X18_SAYBROOK_SOFA_TABLE_SILO_ALT.jpg": {
                "caption": "Saybrook Sofa Table OCA1691C in Oak with 401 Cider Stain with st"
            },
            "https://www.mavinfurniture.com/wp-content/uploads/82X18_SAYBROOK_CONSOLE_TABLE_SILO_HO.jpg": {
                "caption": "Console Table OCA1690B Oak with 407 Black Silk Stain with standa"
            },
            "https://www.mavinfurniture.com/wp-content/uploads/82X18_SAYBROOK_CONSOLE_TABLE_SILO_ALT.jpg": {
                "caption": "Console Table OCA1690B Oak with 407 Black Silk Stain with standa"
            }
        }
    },
    {
        "Category": "Bedroom Collections",
        "Collection": "Bedroom Collections",
        "Collection URL": "https://www.mavinfurniture.com/products/bedrooms/tappan/",
        "Collection Name": "Adrienne",
        "Collection Description": "Inspired by minimalistic Scandinavian reflections, our Tappan bedroom collection proves contemporary design can be warm and welcoming. The simple, clean lines are strong, yet understated, and beautifully fits with both dark and lighter stain choices.",
        "Products": {
            "https://www.mavinfurniture.com/wp-content/uploads/TAPPAN_K_BEDROOM_RS-2.jpg": {
                "caption": "Tappan Dresser 1 TAP18247 with Mirror 4 TAP18304, Tappan Nightstand 4 TAP18244, Tappan King Floating Panel Platform Bed TAP18432. This group was crafted using solid wormy maple with our 317 Gravel stain (nightstand, dresser & mirror) and the bed features a two-tone design with 317 Gravel and 406 Powder stains. The nightstand and dresser also feature Tappan standard hardware K1451-MB (pull)."
            },
            "https://www.mavinfurniture.com/wp-content/uploads/TAPPAN_K_WS_1.jpg": {
                "caption": "Tappan Nightstand 4 TAP18244, Tappan King Floating Panel Platform Bed TAP18432. Crafted using solid wormy maple with our 317 Gravel stain (nightstand) and the bed features a two-tone design with 317 Gravel and 406 Powder stains. The nightstand and dresser also feature Tappan standard hardware K1451-MB (pull)."
            },
            "https://www.mavinfurniture.com/wp-content/uploads/TAPPAN_K_WS_2.jpg": {
                "caption": "Tappan Nightstand 4 TAP18244"
            },
            "https://www.mavinfurniture.com/wp-content/uploads/TAPPAN_K_WS_3.jpg": {
                "caption": "Tappan Dresser 1 with Mirror 4. TAP18247, TAP18304"
            },
            "https://www.mavinfurniture.com/wp-content/uploads/TAPPAN_KING_BEDROOM_RS-New-Hardware.jpg": {
                "caption": "Tappan King Plank Bed with Rail Footboard TAP18132 in solid rustic cherry with our 405 Russett stain (nightstand, dresser & mirror) and 320 Sand (bed & lingerie chest) as well as Tappan standard hardware K1451-MB (pull)."
            },
            "https://www.mavinfurniture.com/wp-content/uploads/TAPPAN_KING_BED_TAP18432-G_SILO_HO-1.jpg": {
                "caption": "Tappan King Floating Panel Platform Bed TAP18432 features a two-tone design with 317 Gravel and 406 Powder stains."
            },
            "https://www.mavinfurniture.com/wp-content/uploads/TAPPAN_KING_BED_TAP18432-G_SILO_ALT-1.jpg": {
                "caption": "Tappan King Floating Panel Platform Bed TAP18432 features a two-tone design with 317 Gravel and 406 Powder stains."
            },
            "https://www.mavinfurniture.com/wp-content/uploads/2022/08/tappan-1.jpg": {
                "caption": "Tappan King Plank Bed with Rail Footboard TAP18132"
            },
            "https://www.mavinfurniture.com/wp-content/uploads/2022/08/77520TAP18132-R_King_Bed_SILO_ALT-hi-1.jpg": {
                "caption": "Tappan King Plank Bed with Rail Footboard TAP18132"
            },
            "https://www.mavinfurniture.com/wp-content/uploads/TAPPAN_NIGHTSTAND-4-TAP18244-G_SILO_HO-1.jpg": {
                "caption": "Tappan Nightstand 4 TAP18244"
            },
            "https://www.mavinfurniture.com/wp-content/uploads/TAPPAN_NIGHTSTAND-4-TAP18244-G_SILO_ALT-1.jpg": {
                "caption": "Tappan Nightstand 4 TAP18244"
            },
            "https://www.mavinfurniture.com/wp-content/uploads/TAPPAN_DRESSER_1-TAP18247-G_SILO_HO.jpg": {
                "caption": "Tappan Dresser 1 TAP18247 with Mirror 4 TAP18304 in solid wormy maple with our 317 Gravel stain and standard hardware K1451-MB (pull)."
            },
            "https://www.mavinfurniture.com/wp-content/uploads/TAPPAN_DRESSER_1-TAP18247-G_SILO_ALT.jpg": {
                "caption": "Tappan Dresser 1 TAP18247 with Mirror 4 TAP18304 in solid wormy maple with our 317 Gravel stain and standard hardware K1451-MB (pull)."
            }
        }
    },
    {
        "Category": "Dining Collections",
        "Collection": "Dining Chairs",
        "Collection URL": "https://www.mavinfurniture.com/products/chairs/weston/",
        "Collection Name": "Weston",
        "Collection Description": null,
        "Products": {
            "https://www.mavinfurniture.com/wp-content/uploads/2022/08/mavin-chairs-Weston-beauty-09.jpg": {
                "caption": "WESTON DINING GROUP: Weston Chair, Wormy Maple Wood Seat, Maple Wood Frame, 400 Belair Stain on the Seat & 402 Mocha Stain on the Frame.  Oval Top Table with one 12\u2033 Leaf, Standard Edge, Single Aurora Pedestal, Wormy Maple Wood Top, Maple Wood Base, 400 Belair Stain on the Top & 402 Mocha Stain on the Base.  Castlebar Server, Wormy Maple Wood Top, Maple Wood Case Body, 400 Belair Stain on the Top & 402 Mocha Stain on the Case Body."
            },
            "https://www.mavinfurniture.com/wp-content/uploads/2022/08/mavin-chairs-Weston-WES6802-2-16.jpg": {
                "caption": "Weston Arm Chair WES6802"
            },
            "https://www.mavinfurniture.com/wp-content/uploads/2022/08/mavin-chairs-Weston-WES6802-15.jpg": {
                "caption": "Weston Arm Chair WES6802"
            },
            "https://www.mavinfurniture.com/wp-content/uploads/2022/08/CHAIRS-WESTON-89225WESTON_SIDE_SILO_3-4_hi.jpg": {
                "caption": "Weston Arm Chair WES6804"
            },
            "https://www.mavinfurniture.com/wp-content/uploads/2022/08/CHAIRS-WESTON-34982WESTON_SIDE_SILO_HO_hi.jpg": {
                "caption": "Weston Arm Chair WES6804"
            }
        }
    },
    {
        "Category": "Dining Collections",
        "Collection": "Dining Chairs",
        "Collection URL": "https://www.mavinfurniture.com/products/chairs/westlake/",
        "Collection Name": "Westlake",
        "Collection Description": null,
        "Products": {
            "https://www.mavinfurniture.com/wp-content/uploads/PLANK_TABLE_w-BREAD-BOARD_RS-2.jpg": {
                "caption": "42\u2033 X 60\u2033 Solid Rectangular Plank Tabletop 4260PA2BBSM-G with Breadboard (2) and EE Standard Edge, Two-tone Wormy Maple in 400 Belair stain. Double Barley Pedestal P2R-G in Wormy Maple and 402 Mocha stain. Westlake Side Chair (6) WST8014-G in Maple and 402 Mocha stain with 322 Dove Grey leather. Hampshire Console HAMC27BS-G x 2 in Wormy Maple and 402 Mocha Stain with standard hardware 6869."
            },
            "https://www.mavinfurniture.com/wp-content/uploads/WESTLAKE_CHAIR_SILO_HO.jpg": {
                "caption": "Westlake"
            },
            "https://www.mavinfurniture.com/wp-content/uploads/WESTLAKE_CHAIR_SILO_ALT.jpg": {
                "caption": "Westlake"
            }
        }
    },
    {
        "Category": "Bedroom Collections",
        "Collection": "Bedroom Collections",
        "Collection URL": "https://www.mavinfurniture.com/products/bedrooms/toulon/",
        "Collection Name": "Adrienne",
        "Collection Description": "Toulon creates a space where classic meets contemporary in perfect harmony. Anchored by a plush upholstered bed, each piece is expertly crafted by skilled artisans, ensuring exceptional quality. The dark stains evoke a sense of sophistication, while the gold hardware adds a lavish touch. With sleek lines and elegant corners, this collection embodies timeless beauty and modern flair, providing a refined and stylish haven for your dreams.",
        "Products": {
            "https://www.mavinfurniture.com/wp-content/uploads/TOULON_K_UPH_BEDROOM_RS-2.jpg": {
                "caption": "Toulon King Upholstered Bed with High Footboard TOU20112, Toulon Nightstand 4 TOU20244, Toulon Dresser 3 TOU20249 and James Mirror JAM10042. This group was crafted using solid rustic cherry with our 407 Black Silk stain, 2308 Gannon fabric and Toulon standard hardware, 484-128160-SBZ (pull) and 484-SBZ (knob)."
            },
            "https://www.mavinfurniture.com/wp-content/uploads/TOULON_K_UPH_BEDROOM_WS_2.jpg": {
                "caption": "Toulon King Upholstered Bed with High Footboard TOU20112 and Toulon Nightstand 4 TOU20244. This group was crafted using solid rustic cherry with our 407 Black Silk stain, 2308 Gannon fabric and Toulon standard hardware, 484-128160-SBZ (pull) and 484-SBZ (knob)."
            },
            "https://www.mavinfurniture.com/wp-content/uploads/TOULON_K_UPH_BEDROOM_WS_3.jpg": {
                "caption": "Toulon Dresser 3 TOU20249 crafted using solid rustic cherry with our 407 Black Silk stain, standard hardware, 484-128160-SBZ (pull) and 484-SBZ (knob)."
            },
            "https://www.mavinfurniture.com/wp-content/uploads/TOULON_K_UPH_BEDROOM_WS_4.jpg": {
                "caption": "Toulon King Upholstered Bed with High Footboard TOU20112 and Toulon Nightstand 4 TOU20244. This group was crafted using solid rustic cherry with our 407 Black Silk stain, 2308 Gannon fabric and Toulon standard hardware, 484-128160-SBZ (pull) and 484-SBZ (knob)."
            },
            "https://www.mavinfurniture.com/wp-content/uploads/TOULON_K_BED_SILO_HO.jpg": {
                "caption": "Toulon King Upholstered Bed with High Footboard TOU20112, Toulon Nightstand 4 TOU20244, Toulon Dresser 3 TOU20249 and James Mirror JAM10042. This group was crafted using solid rustic cherry with our 407 Black Silk stain, 2308 Gannon fabric and Toulon standard hardware, 484-128160-SBZ (pull) and 484-SBZ (knob)."
            },
            "https://www.mavinfurniture.com/wp-content/uploads/TOULON_K_BED_SILO_ALT.jpg": {
                "caption": "Toulon King Upholstered Bed"
            },
            "https://www.mavinfurniture.com/wp-content/uploads/TOULON_DRESSER_3_SILO_HO.jpg": {
                "caption": "Toulon Dresser 3 TOU20249"
            },
            "https://www.mavinfurniture.com/wp-content/uploads/TOULON_DRESSER_3_SILO_ALT.jpg": {
                "caption": "Toulon Dresser 3 TOU20249"
            },
            "https://www.mavinfurniture.com/wp-content/uploads/TOULON_NIGHTSTAND_4_SILO_HO.jpg": {
                "caption": "Toulon Nightstand 4"
            },
            "https://www.mavinfurniture.com/wp-content/uploads/TOULON_NIGHTSTAND_4_SILO_ALT.jpg": {
                "caption": "Toulon Nightstand 4"
            },
            "https://www.mavinfurniture.com/wp-content/uploads/MV_Bedroom02_Toulon_ModernTraditional_Set_01_7200px.jpg": {
                "caption": "Toulon Panel King with High Footboard in 2-tone Oak with 317 Gravel stain with 320 Sand Panels. Nightstand 10, Armoire 1, Dresser 5 and James Mirror in Oak and 317 Gravel stain."
            },
            "https://www.mavinfurniture.com/wp-content/uploads/MV_Bedroom02_Toulon_ModernTraditional_Set_02_7200px.jpg": {
                "caption": "Toulon Panel King with Low Footboard, Nightstand 8, Armoire 1, Dresser 5 and James Mirror in Oak and 317 Gravel stain."
            },
            "https://www.mavinfurniture.com/wp-content/uploads/th-Toulon-Dresser-5-and-James-Mirror.jpg": {
                "caption": "Toulon Dresser 5 and James Mirror"
            },
            "https://www.mavinfurniture.com/wp-content/uploads/TOU20112_Oak_Gravel_320-sand_Angled_noShadow.jpg": {
                "caption": "Toulon Panel King with High Footboard in 2-tone Oak with 317 Gra"
            },
            "https://www.mavinfurniture.com/wp-content/uploads/TOU20112_Oak_Gravel_320-sand_Front_noShadow.jpg": {
                "caption": "Toulon Panel King with High Footboard in 2-tone Oak with 317 Gra"
            },
            "https://www.mavinfurniture.com/wp-content/uploads/TOU20422_Oak_Gravel_noShadow.jpg": {
                "caption": "TOU20422_Oak_Gravel_noShadow"
            },
            "https://www.mavinfurniture.com/wp-content/uploads/TOU20238_Oak_Gravel_noShadow.jpg": {
                "caption": "TOU20238_Oak_Gravel_noShadow"
            },
            "https://www.mavinfurniture.com/wp-content/uploads/TOU20237_Oak_Gravel_noShadow.jpg": {
                "caption": "TOU20237_Oak_Gravel_noShadow"
            },
            "https://www.mavinfurniture.com/wp-content/uploads/TOU20251_Oak_Gravel_noShadow.jpg": {
                "caption": "TOU20251_Oak_Gravel_noShadow"
            },
            "https://www.mavinfurniture.com/wp-content/uploads/TOU20254_Oak_Gravel_noShadow.jpg": {
                "caption": "TOU20254_Oak_Gravel_noShadow"
            },
            "https://www.mavinfurniture.com/wp-content/uploads/TOU20302_Oak_Gravel_noShadow.jpg": {
                "caption": "TOU20302_Oak_Gravel_noShadow"
            }
        }
    },
    {
        "Category": "Dining Collections",
        "Collection": "Dining Chairs",
        "Collection URL": "https://www.mavinfurniture.com/products/chairs/walker/",
        "Collection Name": "Walker",
        "Collection Description": null,
        "Products": {
            "https://www.mavinfurniture.com/wp-content/uploads/MV_DiningRoom_Walker_view-01B.jpg": {
                "caption": "CHAIR: Walker, Maple Wood, 324 Mushroom Leather & 402 Mocha Stain TABLE: Round Top, Standard Edge, Single Madisyn Pedestal, Maple Wood, 410 Honey Stain & Vintage Distressing CASE: Urban Buffet with Hutch, Maple Wood & 410 Honey Stain"
            },
            "https://www.mavinfurniture.com/wp-content/uploads/MV_DiningRoom_Walker_view-01.jpg": {
                "caption": "CHAIR: Walker, Maple Wood, 324 Mushroom Leather & 402 Mocha Stain TABLE: Round Top, Standard Edge, Single Madisyn Pedestal, Maple Wood, 410 Honey Stain & Vintage Distressing CASE: Urban Buffet with Hutch, Maple Wood & 410 Honey Stain"
            },
            "https://www.mavinfurniture.com/wp-content/uploads/MV_DiningRoom_Walker_view-04.jpg": {
                "caption": "CHAIR: Walker, Maple Wood, 324 Mushroom Leather & 402 Mocha Stain TABLE: Round Top, Standard Edge, Single Madisyn Pedestal, Maple Wood, 410 Honey Stain & Vintage Distressing CASE: Urban Buffet with Hutch, Maple Wood & 410 Honey Stain"
            },
            "https://www.mavinfurniture.com/wp-content/uploads/Walker-Caster-Chair_Maple_402-Mocha_324-Mushroom_Angle.jpg": {
                "caption": "Walker Arm Chair WKR8912 Maple, 324 Mushroom Leather & 402 Mocha Stain"
            },
            "https://www.mavinfurniture.com/wp-content/uploads/Walker-Caster-Chair_Maple_402-Mocha_324-Mushroom_Front.jpg": {
                "caption": "Walker Arm Chair WKR8912 Maple, 324 Mushroom Leather & 402 Mocha Stain"
            },
            "https://www.mavinfurniture.com/wp-content/uploads/Walker-Caster-Chair_Walnut_100-Natural_325-Texas_Angle.jpg": {
                "caption": "Walker Arm ChairWKR8912Walnut, 325 Texas Leather & 100 Natural Stain"
            },
            "https://www.mavinfurniture.com/wp-content/uploads/Walker_Caster_Chair_Texas_Front.jpg": {
                "caption": "Walker Arm ChairWKR8912Walnut, 325 Texas Leather & 100 Natural Stain"
            }
        }
    },
    {
        "Category": "Occasional Collection",
        "Collection": "Occasional Collection",
        "Collection URL": "https://www.mavinfurniture.com/products/tables/marco/",
        "Collection Name": "Marco Occasionals",
        "Collection Description": null,
        "Products": {
            "https://www.mavinfurniture.com/wp-content/uploads/Marco-Occasionals-Chairside-Drawers-copy.webp": {
                "caption": "Marco Chairside Table 1 OCA0496A Marco Coffee Table 1 OCA0494C Marco Console Table 2 OCA0490B Marco End Table 2 OCA0492C crafted using rustic cherry with our 400 Belair stain and standard hardware, H076014-SN."
            },
            "https://www.mavinfurniture.com/wp-content/uploads/MARCO_TABLE_WS_1.jpg": {
                "caption": "Marco Coffee Table 1"
            },
            "https://www.mavinfurniture.com/wp-content/uploads/MARCO_TABLE_WS_2.jpg": {
                "caption": "Marco Chairside Table 2"
            },
            "https://www.mavinfurniture.com/wp-content/uploads/MARCO_TABLE_WS_3.jpg": {
                "caption": "Marco Console Table"
            },
            "https://www.mavinfurniture.com/wp-content/uploads/MV_Occasional_Vignette_Marco.jpg": {
                "caption": "MV_Occasional_Vignette_Marco"
            },
            "https://www.mavinfurniture.com/wp-content/uploads/Marco-Chairside-Table_Rustic-Cherry_400Belair_Front.jpg": {
                "caption": "Marco Chairside Table 1 OCA0496A Rustic Cherry, 400 Belair Stain, Standard Hardware: H076014-SN"
            },
            "https://www.mavinfurniture.com/wp-content/uploads/Marco-Chairside-Table_Rustic-Cherry_400Belair_Angled.jpg": {
                "caption": "Marco Chairside Table 1 OCA0496A Rustic Cherry, 400 Belair Stain, Standard Hardware: H076014-SN"
            }
        }
    },
    {
        "Category": "Bedroom Collections",
        "Collection": "Bedroom Collections",
        "Collection URL": "https://www.mavinfurniture.com/products/bedrooms/tribeca/",
        "Collection Name": "Adrienne",
        "Collection Description": "Tribeca sets the perfect stage for relaxed, refined comfort. The balance and symmetry of clean lines and rich details make it a versatile choice to fit any style when a complementing wood species and finish are chosen. Two bed styles complement a variety of coordinating nightstands, dressers, mirrors and chests. All are available in a wood species and finish of your choice.",
        "Products": {
            "https://www.mavinfurniture.com/wp-content/uploads/bedroom-coll-tribeca-panel.jpg": {
                "caption": "Tribeca Dresser 5 TRI14251, with Mirror 5 TRI14305, Tribeca Nightstand 4 TRI14244, Tribeca Chifferobe 2 TRI14257, Tribeca King Panel Bed with High Footboard TRI14112. This group was crafted using solid oak with our 320 Sand stain and Tribeca standard hardware, K6373-128-SIM. Dresser 5 is a two tone item using 304 Charcoal on the case body and 320 Sand stain on the top."
            },
            "https://www.mavinfurniture.com/wp-content/uploads/117258TRI14112-BED-SILOClipped_hi.jpg": {
                "caption": "Tribeca King Panel Bed with High Footboard TRI14112"
            },
            "https://www.mavinfurniture.com/wp-content/uploads/102924TRI14112-BED-SILO-ALTClipped_hi.jpg": {
                "caption": "Tribeca King Panel Bed with High Footboard TRI14112"
            },
            "https://www.mavinfurniture.com/wp-content/uploads/2022/08/62264TRI14244-NIGHTSTAND4Sand-SILO_hi.jpg": {
                "caption": "Tribeca Nightstand 4 TRI14244"
            },
            "https://www.mavinfurniture.com/wp-content/uploads/2022/08/87876TRI14244-NIGHTSTAND4Sand-SILO-ALT_hi.jpg": {
                "caption": "Tribeca Nightstand 4 TRI14244"
            },
            "https://www.mavinfurniture.com/wp-content/uploads/2022/08/88168TRI14280Dresser7CharcoalSand-TRI14304Mirror4Charcoal-SILO-ALT_mirror_hi.jpg": {
                "caption": "Tribeca Dresser 5 TRI14251, with Mirror 5 TRI14305"
            },
            "https://www.mavinfurniture.com/wp-content/uploads/2022/08/117261TRI14257-CHIFFEROBE2Sand-SILO-ALT_hi.jpg": {
                "caption": "Tribeca Chifferobe 2 TRI14257"
            },
            "https://www.mavinfurniture.com/wp-content/uploads/2022/08/21033TRI14251Dresser5CharcoalSand-TRI14305Mirror5Sand-SILO-ALT_hi.jpg": {
                "caption": "Tribeca Dresser 5 TRI14251, with Mirror 5 TRI14305"
            },
            "https://www.mavinfurniture.com/wp-content/uploads/2022/08/47169TRI14270-LINGERIE-CHEST1Charcoal-SILO_hi.jpg": {
                "caption": "Tribeca Lingerie Chest TRI14270"
            },
            "https://www.mavinfurniture.com/wp-content/uploads/2022/08/8436TRI14270-LINGERIE-CHEST1Charcoal-SILO-ALT_hi.jpg": {
                "caption": "Tribeca Lingerie Chest TRI14270"
            },
            "https://www.mavinfurniture.com/wp-content/uploads/92456TRIBECA-WHITE-BEDROOM-3_hi-retouched-3.jpg": {
                "caption": "Tribeca Dresser 2 TRI14248, with Mirror 2 TRI14302, Tribeca Armoire 1 TRI14254, Tribeca Queen Arch Panel Bed with End Drawers TRI14573. This group was crafted using solid oak with our 1P SAV White paint with Savannah glazing and Tribeca standard hardware, K6373-128-SIM."
            },
            "https://www.mavinfurniture.com/wp-content/uploads/42961TRI14573-BED-SILOClipped_hi.jpg": {
                "caption": "Tribeca Queen Arch Panel Bed with End Drawers TRI14573"
            },
            "https://www.mavinfurniture.com/wp-content/uploads/39803TRI14573-BED-SILO-ALTClipped_hi.jpg": {
                "caption": "Tribeca Queen Arch Panel Bed with End Drawers TRI14573"
            },
            "https://www.mavinfurniture.com/wp-content/uploads/58128TRI14254-ARMOIRE-SILO_hi.jpg": {
                "caption": "Tribeca Armoire 1 TRI14254"
            },
            "https://www.mavinfurniture.com/wp-content/uploads/13081TRI14254-ARMOIRE-SILO-ALT_hi.jpg": {
                "caption": "Tribeca Armoire 1 TRI14254"
            },
            "https://www.mavinfurniture.com/wp-content/uploads/111660TRI14248-14303-SILO_hi.jpg": {
                "caption": "Tribeca Dresser 2 TRI14248, with Mirror 2 TRI14302"
            },
            "https://www.mavinfurniture.com/wp-content/uploads/104067TRI14248-14303-SILO-ALT_hi.jpg": {
                "caption": "Tribeca Dresser 2 TRI14248, with Mirror 2 TRI14302"
            }
        }
    },
    {
        "Category": "Dining Collections",
        "Collection": "Dining Chairs",
        "Collection URL": "https://www.mavinfurniture.com/products/chairs/thea/",
        "Collection Name": "Thea",
        "Collection Description": null,
        "Products": {
            "https://www.mavinfurniture.com/wp-content/uploads/2022/11/4884P_plank_table_-thea_rs.jpg": {
                "caption": "Thea Side Chair, THA7714, with 2206 Luna fabric, with 402 Mocha stain on legs. Plank Table in 401 Cider finish, with Double Madisyn pedestal in 402 Mocha finish. Thea Side Chair, THA7714, with 333 Cloudy Day Leather fabric, with 402 Mocha stain on legs."
            },
            "https://www.mavinfurniture.com/wp-content/uploads/2022/11/thea_chair_2206_luna_silo_ALT.jpg": {
                "caption": "Thea Side Chair THA7714"
            },
            "https://www.mavinfurniture.com/wp-content/uploads/2022/11/thea_chair_2206_luna_silo_ho.jpg": {
                "caption": "Thea Side Chair THA7714"
            }
        }
    },
    {
        "Category": "Dining Collections",
        "Collection": "Dining Chairs",
        "Collection URL": "https://www.mavinfurniture.com/products/chairs/norwalk/",
        "Collection Name": "Norwalk",
        "Collection Description": null,
        "Products": {
            "https://www.mavinfurniture.com/wp-content/uploads/2022/08/mavin-chairs-Norwalk-beauty-04.jpg": {
                "caption": "Norwalk Chair, Maple Wood, 2014 COM Fabric & 405 Russett Stain. Round Top Table, Curved Edge, Single Aurora Pedestal, Maple Wood & 405 Russett Stain. Zayne Buffet, Maple Wood & 405 Russett Stain."
            },
            "https://www.mavinfurniture.com/wp-content/uploads/2022/08/mavin-chairs-Norwalk-NOR7114-02.jpg": {
                "caption": "Norwalk Side Chair NOR7114"
            },
            "https://www.mavinfurniture.com/wp-content/uploads/2022/08/mavin-chairs-Norwalk-NOR7114-2-03.jpg": {
                "caption": "Norwalk Side Chair NOR7114"
            }
        }
    },
    {
        "Category": "Dining Collections",
        "Collection": "Dining Chairs",
        "Collection URL": "https://www.mavinfurniture.com/products/chairs/rialto/",
        "Collection Name": "Rialto",
        "Collection Description": null,
        "Products": {
            "https://www.mavinfurniture.com/wp-content/uploads/2022/08/mavin-chairs-Rialto-beauty-01.jpg": {
                "caption": "RIALTO DINING GROUP: Rialto Chair, Rustic Cherry Wood & 7992 Asbury Stain.  Rectangular Top Table with one 18\u2033 Leaf, Standard Edge, Double Rialto Pedestal, Rustic Cherry Wood & 7992 Asbury Stain."
            },
            "https://www.mavinfurniture.com/wp-content/uploads/2022/08/mavin-chairs-Rialto-RIA6302-06.jpg": {
                "caption": "Rialto Arm Chair RIA6302"
            },
            "https://www.mavinfurniture.com/wp-content/uploads/2022/08/mavin-chairs-Rialto-RIA6302-2-08.jpg": {
                "caption": "Rialto Arm Chair RIA6302"
            },
            "https://www.mavinfurniture.com/wp-content/uploads/2022/08/mavin-chairs-Rialto-RIA6304-2-07.jpg": {
                "caption": "Rialto Side Chair RIA6304"
            },
            "https://www.mavinfurniture.com/wp-content/uploads/2022/08/mavin-chairs-Rialto-RIA6304-04.jpg": {
                "caption": "Rialto Side Chair RIA6304"
            }
        }
    },
    {
        "Category": "Dining Collections",
        "Collection": "Dining Chairs",
        "Collection URL": "https://www.mavinfurniture.com/products/chairs/manhattan/",
        "Collection Name": "Manhattan",
        "Collection Description": null,
        "Products": {
            "https://www.mavinfurniture.com/wp-content/uploads/2022/08/mavin-chairs-Manhattan-beauty-02.jpg": {
                "caption": "Manhattan Chair, Maple Wood, 104 COM Fabric & 230 Onyx Stain."
            },
            "https://www.mavinfurniture.com/wp-content/uploads/2022/08/mavin-chairs-Manhattan-MAN2704-2-05.jpg": {
                "caption": "Manhattan Side Chair MAN2714"
            }
        }
    },
    {
        "Category": "Dining Collections",
        "Collection": "Dining Cases",
        "Collection URL": "https://www.mavinfurniture.com/products/cases/monterey-console/",
        "Collection Name": "Monterey Console",
        "Collection Description": null,
        "Products": {
            "https://www.mavinfurniture.com/wp-content/uploads/5454_DINING_WS_1.jpg": {
                "caption": "Square Table 5454A000-W in Quartersawn Oak with EC Bevel and P1A Cadiz base in 100 Natural stain. Solon Side Chairs SOL7914 in Oak with 32P Raincloud and 2305 Riverrock fabric. Small Monterey Console MONC32CS-Q in Quarter Sawn Oak with 100 Natural stain and standard hardware."
            },
            "https://www.mavinfurniture.com/wp-content/uploads/5454_DINING_DETAILS_3.jpg": {
                "caption": "Small Monterey Console MONC32CS-Q in Quarter Sawn Oak with 100 Natural stain and standard hardware."
            },
            "https://www.mavinfurniture.com/wp-content/uploads/3872_CONCAVE_DINING_WS_1.jpg": {
                "caption": "Concave Table Top, with Kirby Side Chairs in Walnut and 2401 fabric, Large Montery Console MONC32CL in Walnut and 100 Natural stain with standard hardware."
            },
            "https://www.mavinfurniture.com/wp-content/uploads/3872_CONCAVE_DINING_WORKING-SHOT_3.jpg": {
                "caption": "Large Montery Console MONC32CL in Walnut and 100 Natural stain with standard hardware."
            },
            "https://www.mavinfurniture.com/wp-content/uploads/SM_MONTEREY_CONSOLE_SILO_HO.jpg": {
                "caption": "Monterey Small Console MONC32CSL"
            },
            "https://www.mavinfurniture.com/wp-content/uploads/SM_MONTEREY_CONSOLE_SILO_ALT.jpg": {
                "caption": "Monterey Small Console MONC32CSL"
            },
            "https://www.mavinfurniture.com/wp-content/uploads/MONTEREY_CONSOLE_SILO_ALT.jpg": {
                "caption": "Monterey Large Console MONC32CSS"
            },
            "https://www.mavinfurniture.com/wp-content/uploads/MONTEREY_CONSOLE_SILO_HO.jpg": {
                "caption": "Monterey Large Console MONC32CSS"
            }
        }
    },
    {
        "Category": "Dining Collections",
        "Collection": "Dining Cases",
        "Collection URL": "https://www.mavinfurniture.com/products/cases/toulon/",
        "Collection Name": "Toulon Server",
        "Collection Description": null,
        "Products": {
            "https://www.mavinfurniture.com/wp-content/uploads/4272_COSMO_DINING_RS.jpg": {
                "caption": "Solid Cosmo Table 4272K000-R in EE standard top in Rustic Cherry and Tropez Leg L30 in 407 Black Silk stain. Dallas Side DAL8214 and Arm Chairs DAL8212 in Rustic Cherry with 407 Black Silk stain and 2407 Camelus fabric. Toulon Server TOUC34SS in Rustic Cherry and 407 Black Silk stain with standard hardware."
            },
            "https://www.mavinfurniture.com/wp-content/uploads/4272_COSMO_DINING_WS_2.jpg": {
                "caption": "Solid Cosmo Table 4272K000-R in EE standard top in Rustic Cherry and Tropez Leg L30 in 407 Black Silk stain. Dallas Side DAL8214 and Arm Chairs DAL8212 in Rustic Cherry with 407 Black Silk stain and 2407 Camelus fabric. Toulon Server TOUC34SS in Rustic Cherry and 407 Black Silk stain with standard hardware."
            },
            "https://www.mavinfurniture.com/wp-content/uploads/TOULON_SERVER_SILO_HO.jpg": {
                "caption": "Toulon Server TOUC34SS"
            },
            "https://www.mavinfurniture.com/wp-content/uploads/TOULON_SERVER_SILO_ALT.jpg": {
                "caption": "Toulon Server TOUC34SS"
            }
        }
    },
    {
        "Category": "Dining Collections",
        "Collection": "Dining Chairs",
        "Collection URL": "https://www.mavinfurniture.com/products/chairs/rochester/",
        "Collection Name": "Rochester",
        "Collection Description": null,
        "Products": {
            "https://www.mavinfurniture.com/wp-content/uploads/2022/08/mavin-chairs-Rochester-beauty-03.jpg": {
                "caption": "ROCHESTER DINING GROUP: Rochester Chair, Oak Wood, 172 Ecru Fabric, 402 Mocha Stain & Vintage Distressing.  Rectangular Top Table with one 18\u2033 Leaf, Curved Edge, Farmhouse Leg, Oak Wood, 402 Mocha Stain on the Top, 1P SAV White with Savannah Glaze on the Base & Vintage Distressing.  Kennedy Sideboard, Oak Wood, 402 Mocha Stain on the Top, 1P SAV White with Savannah Glaze on the Case Body, Vintage Distressing & Ring Pull Hardware 920240-904."
            },
            "https://www.mavinfurniture.com/wp-content/uploads/2022/08/mavin-chairs-Rochester-RCH1204-2-07.jpg": {
                "caption": "Rochester Side Chair RCH1214"
            },
            "https://www.mavinfurniture.com/wp-content/uploads/2022/08/mavin-chairs-Rochester-RCH1204-3-08.jpg": {
                "caption": "Rochester Side Chair RCH1214"
            }
        }
    },
    {
        "Category": "Dining Collections",
        "Collection": "Dining Chairs",
        "Collection URL": "https://www.mavinfurniture.com/products/chairs/percy/",
        "Collection Name": "Percy",
        "Collection Description": null,
        "Products": {
            "https://www.mavinfurniture.com/wp-content/uploads/2022/08/mavin-chairs-Percy-beauty-01.jpg": {
                "caption": "PERCY DINING GROUP: Percy Chair, Maple Wood & 3P PRT Black Paint with Paint Rub Thru.  Rectangular Plank Top Table, Standard Edge, Rietta Leg, Oak Wood & 100 Natural Stain.  Metro Buffet with Hutch, Maple Wood & 1P White Paint."
            },
            "https://www.mavinfurniture.com/wp-content/uploads/2022/08/mavin-chairs-Percy-PER7304-05.jpg": {
                "caption": "Percy Side Chair PER7304"
            },
            "https://www.mavinfurniture.com/wp-content/uploads/2022/08/mavin-chairs-Percy-PER7304-3-06.jpg": {
                "caption": "Percy Side Chair PER7304"
            }
        }
    },
    {
        "Category": "Dining Collections",
        "Collection": "Dining Cases",
        "Collection URL": "https://www.mavinfurniture.com/products/cases/saybrook-console/",
        "Collection Name": "Saybrook Console",
        "Collection Description": null,
        "Products": {
            "https://www.mavinfurniture.com/wp-content/uploads/SAYBROOK_CONSOLE_VIGN.jpg": {
                "caption": "SAYBROOK_CONSOLE_VIGN"
            },
            "https://www.mavinfurniture.com/wp-content/uploads/SAYBROOK_CONSOLE_WS_1.jpg": {
                "caption": "SAYBROOK_CONSOLE_WS_1"
            },
            "https://www.mavinfurniture.com/wp-content/uploads/SAYBROOK_CONSOLE_WS_2.jpg": {
                "caption": "SAYBROOK_CONSOLE_WS_2"
            },
            "https://www.mavinfurniture.com/wp-content/uploads/SAYBROOK_CONSOLE_DETAILS_1.jpg": {
                "caption": "SAYBROOK_CONSOLE_DETAILS_1"
            },
            "https://www.mavinfurniture.com/wp-content/uploads/th-Saybrook-Console-SAYC31CS.jpg": {
                "caption": "Saybrook Console SAYC31CS"
            },
            "https://www.mavinfurniture.com/wp-content/uploads/SAYBROOK_CONSOLE_HO.jpg": {
                "caption": "Saybrook Console SAYC31CS"
            },
            "https://www.mavinfurniture.com/wp-content/uploads/SAYBROOK_CONSOLE_ALT.jpg": {
                "caption": "Saybrook Console SAYC31CS"
            },
            "https://www.mavinfurniture.com/wp-content/uploads/Saybrook_Small_Console_Front-2.jpg": {
                "caption": "Saybrook Small Console SAYC31CSS Oak & 411 Wheat Stain Custom Hardware Shown: TK1016BLK"
            },
            "https://www.mavinfurniture.com/wp-content/uploads/Saybrook_Small_Console_Angle.jpg": {
                "caption": "Saybrook Small Console SAYC31CSS Oak & 411 Wheat Stain Custom Hardware Shown: TK1016BLK"
            }
        }
    },
    {
        "Category": "Dining Collections",
        "Collection": "Dining Chairs",
        "Collection URL": "https://www.mavinfurniture.com/products/chairs/dutton/",
        "Collection Name": "Dutton",
        "Collection Description": null,
        "Products": {
            "https://www.mavinfurniture.com/wp-content/uploads/MV_DiningRoom_Dutton_view01.jpg": {
                "caption": "CHAIR: Dutton, Quarter Sawn Oak Wood, 2408 Cascade Fabric & 402 Mocha Stain TABLE: Square Top, Bevel Edge, Quarter Sawn Oak Wood, 400 Belair Stain, Single Cadiz Pedestal, Quarter Sawn Oak Wood & 402 Mocha Stain CASE: Zayne Sideboard, Quarter Sawn Oak Wood & 400 Belair Stain"
            },
            "https://www.mavinfurniture.com/wp-content/uploads/MV_DiningRoom_Dutton_view02.jpg": {
                "caption": "CHAIR: Dutton, Quarter Sawn Oak Wood, 2408 Cascade Fabric & 402 Mocha Stain TABLE: Square Top, Bevel Edge, Quarter Sawn Oak Wood, 400 Belair Stain, Single Cadiz Pedestal, Quarter Sawn Oak Wood & 402 Mocha Stain CASE: Zayne Sideboard, Quarter Sawn Oak Wood & 400 Belair Stain"
            },
            "https://www.mavinfurniture.com/wp-content/uploads/Dutton-Caster-Chair_Qt-SawOak_402-Mocha_2408-Cascade_Front.jpg": {
                "caption": "Dutton Caster Chair_Qt SawOak_402 Mocha_2408 Cascade_Front"
            },
            "https://www.mavinfurniture.com/wp-content/uploads/Dutton-Caster-Chair_Qt-SawOak_402-Mocha_2408-Cascade_Angle.jpg": {
                "caption": "Dutton Caster Chair_Qt SawOak_402 Mocha_2408 Cascade_Angle"
            }
        }
    },
    {
        "Category": "Dining Collections",
        "Collection": "Dining Chairs",
        "Collection URL": "https://www.mavinfurniture.com/products/chairs/brinkley/",
        "Collection Name": "Brinkley",
        "Collection Description": null,
        "Products": {
            "https://www.mavinfurniture.com/wp-content/uploads/2022/08/mavin-chairs-brinkley-beauty.jpg": {
                "caption": "BRINKLEY DINING GROUP: Brinkley Chair, Quarter Sawn Oak Wood Seat / Top Rail, Maple Wood Frame, 113 Michaels Stain on the Seat / Top Rail & 230 Onyx Stain on the Frame.  Boat Top Table with one 18\u2033 Leaf, Curved Edge, Victor Leg, Quarter Sawn Oak Wood Top, Maple Wood Base, 113 Michaels Stain on the Top & 230 Onyx Stain on the Base.  Stafford Buffet, Quarter Sawn Oak Wood Doors / Drawers / Top, Maple Wood Frame, 113 Michaels Stain on the Doors / Drawers / Top & 230 Onyx Stain on the Frame."
            },
            "https://www.mavinfurniture.com/wp-content/uploads/2022/08/mavin-chairs-brinkley-BNK5804-2.jpg": {
                "caption": "Brinkley Side Chair BNK5804"
            },
            "https://www.mavinfurniture.com/wp-content/uploads/2022/08/mavin-chairs-brinkley-BNK5804.jpg": {
                "caption": "Brinkley Side Chair BNK5804"
            },
            "https://www.mavinfurniture.com/wp-content/uploads/2022/08/mavin-chairs-brinkley-BNK5802-2.jpg": {
                "caption": "Brinkley Arm Chair BNK5802"
            },
            "https://www.mavinfurniture.com/wp-content/uploads/2022/08/mavin-chairs-brinkley-BNK5802.jpg": {
                "caption": "Brinkley Arm Chair BNK5802"
            }
        }
    }
]